[{"Slug":"payment-card-validation69","Title":"Payment-Card-Validation69","Description":"A new Flutter application demonstrating how to validate payment card number, cvv and date.","GitHubRepoInfo":{"GitHubRepoName":"wilburt/Payment-Card-Validation","full_name":null,"description":null,"stargazers_count":0,"forks_count":0,"pushed_at":"0001-01-01T00:00:00"},"ExternalUri":null,"ContainsAndroidSample":true,"ContainsiOSSample":true,"ContainsUWPSample":false,"AuthorInfo":{"FirstName":"wilburt","LastName":"","Website":"http://wilburx9.dev/","TwitterHandle":"wilburt","GitHubHandle":"wilburt","GravatarHash":""},"ImageUris":["https://raw.githubusercontent.com/wilburt/Payment-Card-Validation/master/screenshots/screenshot1.png"],"Categories":[25,39,21]},{"Slug":"payment-card-validation89","Title":"Payment-Card-Validation89","Description":"A new Flutter application demonstrating how to validate payment card number, cvv and date.","GitHubRepoInfo":{"GitHubRepoName":"wilburt/Payment-Card-Validation","full_name":null,"description":null,"stargazers_count":0,"forks_count":0,"pushed_at":"0001-01-01T00:00:00"},"ExternalUri":null,"ContainsAndroidSample":true,"ContainsiOSSample":true,"ContainsUWPSample":false,"AuthorInfo":{"FirstName":"wilburt","LastName":"","Website":"http://wilburx9.dev/","TwitterHandle":"wilburt","GitHubHandle":"wilburt","GravatarHash":""},"ImageUris":["https://raw.githubusercontent.com/wilburt/Payment-Card-Validation/master/screenshots/screenshot1.png"],"Categories":[25,19,11]},{"Slug":"payment-card-validation148","Title":"Payment-Card-Validation148","Description":"A new Flutter application demonstrating how to validate payment card number, cvv and date.","GitHubRepoInfo":{"GitHubRepoName":"wilburt/Payment-Card-Validation","full_name":null,"description":null,"stargazers_count":0,"forks_count":0,"pushed_at":"0001-01-01T00:00:00"},"ExternalUri":null,"ContainsAndroidSample":true,"ContainsiOSSample":true,"ContainsUWPSample":false,"AuthorInfo":{"FirstName":"wilburt","LastName":"","Website":"http://wilburx9.dev/","TwitterHandle":"wilburt","GitHubHandle":"wilburt","GravatarHash":""},"ImageUris":["https://raw.githubusercontent.com/wilburt/Payment-Card-Validation/master/screenshots/screenshot1.png"],"Categories":[25,15,31]},{"Slug":"payment-card-validation188","Title":"Payment-Card-Validation188","Description":"A new Flutter application demonstrating how to validate payment card number, cvv and date.","GitHubRepoInfo":{"GitHubRepoName":"wilburt/Payment-Card-Validation","full_name":null,"description":null,"stargazers_count":0,"forks_count":0,"pushed_at":"0001-01-01T00:00:00"},"ExternalUri":null,"ContainsAndroidSample":true,"ContainsiOSSample":true,"ContainsUWPSample":false,"AuthorInfo":{"FirstName":"wilburt","LastName":"","Website":"http://wilburx9.dev/","TwitterHandle":"wilburt","GitHubHandle":"wilburt","GravatarHash":""},"ImageUris":["https://raw.githubusercontent.com/wilburt/Payment-Card-Validation/master/screenshots/screenshot1.png"],"Categories":[25,3,3]},{"Slug":"payment-card-validation217","Title":"Payment-Card-Validation217","Description":"A new Flutter application demonstrating how to validate payment card number, cvv and date.","GitHubRepoInfo":{"GitHubRepoName":"wilburt/Payment-Card-Validation","full_name":null,"description":null,"stargazers_count":0,"forks_count":0,"pushed_at":"0001-01-01T00:00:00"},"ExternalUri":null,"ContainsAndroidSample":true,"ContainsiOSSample":true,"ContainsUWPSample":false,"AuthorInfo":{"FirstName":"wilburt","LastName":"","Website":"http://wilburx9.dev/","TwitterHandle":"wilburt","GitHubHandle":"wilburt","GravatarHash":""},"ImageUris":["https://raw.githubusercontent.com/wilburt/Payment-Card-Validation/master/screenshots/screenshot1.png"],"Categories":[25,19,29]},{"Slug":"payment-card-validation240","Title":"Payment-Card-Validation240","Description":"A new Flutter application demonstrating how to validate payment card number, cvv and date.","GitHubRepoInfo":{"GitHubRepoName":"wilburt/Payment-Card-Validation","full_name":null,"description":null,"stargazers_count":0,"forks_count":0,"pushed_at":"0001-01-01T00:00:00"},"ExternalUri":null,"ContainsAndroidSample":true,"ContainsiOSSample":true,"ContainsUWPSample":false,"AuthorInfo":{"FirstName":"wilburt","LastName":"","Website":"http://wilburx9.dev/","TwitterHandle":"wilburt","GitHubHandle":"wilburt","GravatarHash":""},"ImageUris":["https://raw.githubusercontent.com/wilburt/Payment-Card-Validation/master/screenshots/screenshot1.png"],"Categories":[25,23,6]}]